setup.py
./hst/bin/hst
hst/__init__.py
hst/hst.py
hst/indexer.py
hst/levenshtein.py
hst/matcher.py
hst.egg-info/PKG-INFO
hst.egg-info/SOURCES.txt
hst.egg-info/dependency_links.txt
hst.egg-info/requires.txt
hst.egg-info/top_level.txt