Metadata-Version: 1.1
Name: hst
Version: 0.1.8
Summary: history search & picker in ncurses - also can pick other things
Home-page: http://github.com/ybrs/hst
Author: ybrs
Author-email: aybars.badur@gmail.com
License: MIT
Platform: UNKNOWN
Classifier: Development Status :: 4 - Beta
Classifier: Intended Audience :: Developers
Classifier: License :: OSI Approved :: MIT License
Classifier: Operating System :: OS Independent
Classifier: Programming Language :: Python
Classifier: Topic :: Database
Classifier: Topic :: Software Development :: Libraries :: Python Modules
